LFSR.v
`default_nettype none

module LFSR(
    input   wire clk_i,
    input   wire rst_i,
    output  wire [15:0] d_o
);

    reg [15:0] d;
    assign d_o = d;
    wire feedback = d[15] ^ d[13] ^ d[12] ^ d[10];

    always @(posedge clk_i) begin
        if (!rst_i) begin
            d <= 16'habcd;
        end else begin
            d <= {d[14:0], feedback};
        end
    end

endmodule

RNG.v
`default_nettype none

module RNG(
    input wire clk_i,
    input wire rst_i,
    input wire [15:0] in_i,
    output wire d_o
);

    wire [15:0] random_number;
    LFSR lfsr(
        .clk_i(clk_i),
        .rst_i(rst_i),
        .d_o(random_number)
    );

    assign d_o = (random_number < in_i);
endmodule

top.v

`default_nettype none

module top(
    input wire clk_i,
    input wire rst_i
);

    initial begin
        $dumpfile("dump.vcd");
        $dumpvars(0);
    end
    
    reg [31:0] cnt = 0;
    reg [31:0] rng_cnt = 0;

    wire SNs;
    RNG rng(
        .clk_i(clk_i),
        .rst_i(rst_i),
        .in_i(16'h7fff),
        .d_o(SNs)
    );

    always @(posedge clk_i) begin
        cnt <= cnt + 1;
        
        if(SNs)rng_cnt <= rng_cnt + 1;

        if (cnt == 32'd10000)begin
            $display("rng_cnt = %d", rng_cnt);
            $finish;
        end
    end
endmodule

dump.vcd
$version Generated by VerilatedVcd $end
$timescale 1ps $end

 $scope module TOP $end
  $var wire  1 ( clk_i $end
  $var wire  1 ) rst_i $end
  $scope module top $end
   $var wire  1 % SNs $end
   $var wire  1 ( clk_i $end
   $var wire 32 # cnt [31:0] $end
   $var wire 32 $ rng_cnt [31:0] $end
   $var wire  1 ) rst_i $end
   $scope module rng $end
    $var wire  1 ( clk_i $end
    $var wire  1 % d_o $end
    $var wire 16 * in_i [15:0] $end
    $var wire 16 & random_number [15:0] $end
    $var wire  1 ) rst_i $end
    $scope module lfsr $end
     $var wire  1 ( clk_i $end
     $var wire 16 & d [15:0] $end
     $var wire 16 & d_o [15:0] $end
     $var wire  1 ' feedback $end
     $var wire  1 ) rst_i $end
    $upscope $end
   $upscope $end
  $upscope $end
 $upscope $end
$enddefinitions $end


#1
b00000000000000000000000000000000 #
b00000000000000000000000000000000 $
1%
b0000000000000000 &
0'
1(
0)
b0111111111111111 *
#2
0(
#3
b00000000000000000000000000000001 #
b00000000000000000000000000000001 $
0%
b1010101111001101 &
1(
#4
0(
#5
b00000000000000000000000000000010 #
1(
#6
0(
#7
b00000000000000000000000000000011 #
1(
#8
0(
#9
b00000000000000000000000000000100 #
1(
#10
0(
#11
b00000000000000000000000000000101 #
1%
b0101011110011010 &
1(
1)
#12
0(
#13
b00000000000000000000000000000110 #
b00000000000000000000000000000010 $
0%
b1010111100110100 &
1'
1(
#14
0(
#15
b00000000000000000000000000000111 #
1%
b0101111001101001 &
0'
1(
#16
0(
#17
b00000000000000000000000000001000 #
b00000000000000000000000000000011 $
0%
b1011110011010010 &
1(
#18
0(
#19
b00000000000000000000000000001001 #
1%
b0111100110100100 &
1(
#20
0(
#21
b00000000000000000000000000001010 #
b00000000000000000000000000000100 $
0%
b1111001101001000 &
1'
1(
#22
0(
#23
b00000000000000000000000000001011 #
b1110011010010001 &
1(
#24
0(
#25
b00000000000000000000000000001100 #
b1100110100100011 &
0'
1(
#26
0(
#27
b00000000000000000000000000001101 #
b1001101001000110 &
1(
#28
0(
#29
b00000000000000000000000000001110 #
1%
b0011010010001100 &
1'
1(
#30
0(
#31
b00000000000000000000000000001111 #
b00000000000000000000000000000101 $
b0110100100011001 &
1(
#32
0(
#33
b00000000000000000000000000010000 #
b00000000000000000000000000000110 $
0%
b1101001000110011 &
0'
1(
#34
0(
#35
b00000000000000000000000000010001 #
b1010010001100110 &
1'
1(
#36
0(
#37
b00000000000000000000000000010010 #
1%
b0100100011001101 &
0'
1(
#38
0(
#39
b00000000000000000000000000010011 #
b00000000000000000000000000000111 $
0%
b1001000110011010 &
1(
#40
0(
#41
b00000000000000000000000000010100 #
1%
b0010001100110100 &
1'
1(
#42
0(
#43
b00000000000000000000000000010101 #
b00000000000000000000000000001000 $
b0100011001101001 &
1(
#44
0(
#45
b00000000000000000000000000010110 #
b00000000000000000000000000001001 $
0%
b1000110011010011 &
0'
1(
#46
0(
#47
b00000000000000000000000000010111 #
1%
b0001100110100110 &
1'
1(
#48
0(
#49
b00000000000000000000000000011000 #
b00000000000000000000000000001010 $
b0011001101001101 &
0'
1(
#50
0(
#51
b00000000000000000000000000011001 #
b00000000000000000000000000001011 $
b0110011010011010 &
1(
#52
0(
#53
b00000000000000000000000000011010 #
b00000000000000000000000000001100 $
0%
b1100110100110100 &
1(
#54
0(
#55
b00000000000000000000000000011011 #
b1001101001101000 &
1(
#56
0(
#57
b00000000000000000000000000011100 #
1%
b0011010011010000 &
1'
1(
#58
0(
#59
b00000000000000000000000000011101 #
b00000000000000000000000000001101 $
b0110100110100001 &
1(
#60
0(
#61
b00000000000000000000000000011110 #
b00000000000000000000000000001110 $
0%
b1101001101000011 &
0'
1(
#62
0(
#63
b00000000000000000000000000011111 #
b1010011010000110 &
1'
1(
#64
0(
#65
b00000000000000000000000000100000 #
1%
b0100110100001101 &
1(
#66
0(
#67
b00000000000000000000000000100001 #
b00000000000000000000000000001111 $
0%
b1001101000011011 &
0'
1(
#68
0(
#69
b00000000000000000000000000100010 #
1%
b0011010000110110 &
1'
1(
#70
0(
#71
b00000000000000000000000000100011 #
b00000000000000000000000000010000 $
b0110100001101101 &
1(
#72
0(
#73
b00000000000000000000000000100100 #
b00000000000000000000000000010001 $
0%
b1101000011011011 &
0'
1(
#74
0(
#75
b00000000000000000000000000100101 #
b1010000110110110 &
1(
#76
0(
#77
b00000000000000000000000000100110 #
1%
b0100001101101100 &
1(
#78
0(
#79
b00000000000000000000000000100111 #
b00000000000000000000000000010010 $
0%
b1000011011011000 &
1(
#80
0(
#81
b00000000000000000000000000101000 #
1%
b0000110110110000 &
1'
1(
#82
0(
#83
b00000000000000000000000000101001 #
b00000000000000000000000000010011 $
b0001101101100001 &
1(
#84
0(
#85
b00000000000000000000000000101010 #
b00000000000000000000000000010100 $
b0011011011000011 &
1(
#86
0(
#87
b00000000000000000000000000101011 #
b00000000000000000000000000010101 $
b0110110110000111 &
0'
1(
#88
0(
#89
b00000000000000000000000000101100 #
b00000000000000000000000000010110 $
0%
b1101101100001110 &
1(
#90
0(
#91
b00000000000000000000000000101101 #
b1011011000011100 &
1(
#92
0(
#93
b00000000000000000000000000101110 #
1%
b0110110000111000 &
1(
#94
0(
#95
b00000000000000000000000000101111 #
b00000000000000000000000000010111 $
0%
b1101100001110000 &
1(
#96
0(
#97
b00000000000000000000000000110000 #
b1011000011100000 &
1'
1(
#98
0(
#99
b00000000000000000000000000110001 #
1%
b0110000111000001 &
1(
#100
0(
#101
b00000000000000000000000000110010 #
b00000000000000000000000000011000 $
0%
b1100001110000011 &
1(
#102
0(
#103
b00000000000000000000000000110011 #
b1000011100000111 &
0'
1(
#104
0(
#105
b00000000000000000000000000110100 #
1%
b0000111000001110 &
1'
1(
#106
0(
#107
b00000000000000000000000000110101 #
b00000000000000000000000000011001 $
b0001110000011101 &
0'
1(
#108
0(
#109
b00000000000000000000000000110110 #
b00000000000000000000000000011010 $
b0011100000111010 &
1(
#110
0(
#111
b00000000000000000000000000110111 #
b00000000000000000000000000011011 $
b0111000001110100 &
1(
#112
0(
#113
b00000000000000000000000000111000 #
b00000000000000000000000000011100 $
0%
b1110000011101000 &
1(
#114
0(
#115
b00000000000000000000000000111001 #
b1100000111010000 &
1'
1(
#116
0(
#117
b00000000000000000000000000111010 #
b1000001110100001 &
1(
#118
0(
#119
b00000000000000000000000000111011 #
1%
b0000011101000011 &
1(
#120
0(
#121
b00000000000000000000000000111100 #
b00000000000000000000000000011101 $
b0000111010000111 &
1(
#122
0(
#123
b00000000000000000000000000111101 #
b00000000000000000000000000011110 $
b0001110100001111 &
0'
1(
#124
0(
#125
b00000000000000000000000000111110 #
b00000000000000000000000000011111 $
b0011101000011110 &
1(
#126
0(
#127
b00000000000000000000000000111111 #
b00000000000000000000000000100000 $
b0111010000111100 &
1'
1(
#128
0(
#129
b00000000000000000000000001000000 #
b00000000000000000000000000100001 $
0%
b1110100001111001 &
0'
1(
#130
0(
#131
b00000000000000000000000001000001 #
b1101000011110010 &
1(
#132
0(
#133
b00000000000000000000000001000010 #
b1010000111100100 &
1(
#134
0(
#135
b00000000000000000000000001000011 #
1%
b0100001111001000 &
1(
#136
0(
#137
b00000000000000000000000001000100 #
b00000000000000000000000000100010 $
0%
b1000011110010000 &
1(
#138
0(
#139
b00000000000000000000000001000101 #
1%
b0000111100100000 &
1'
1(
#140
0(
#141
b00000000000000000000000001000110 #
b00000000000000000000000000100011 $
b0001111001000001 &
0'
1(
#142
0(
#143
b00000000000000000000000001000111 #
b00000000000000000000000000100100 $
b0011110010000010 &
1'
1(
#144
0(
#145
b00000000000000000000000001001000 #
b00000000000000000000000000100101 $
b0111100100000101 &
0'
1(
#146
0(
#147
b00000000000000000000000001001001 #
b00000000000000000000000000100110 $
0%
b1111001000001010 &
1'
1(
#148
0(
#149
b00000000000000000000000001001010 #
b1110010000010101 &
1(
#150
0(
#151
b00000000000000000000000001001011 #
b1100100000101011 &
1(
#152
0(
#153
b00000000000000000000000001001100 #
b1001000001010111 &
0'
1(
#154
0(
#155
b00000000000000000000000001001101 #
1%
b0010000010101110 &
1'
1(
#156
0(
#157
b00000000000000000000000001001110 #
b00000000000000000000000000100111 $
b0100000101011101 &
0'
1(
#158
0(
#159
b00000000000000000000000001001111 #
b00000000000000000000000000101000 $
0%
b1000001010111010 &
1'
1(
#160
0(
#161
b00000000000000000000000001010000 #
1%
b0000010101110101 &
1(
#162
0(
#163
b00000000000000000000000001010001 #
b00000000000000000000000000101001 $
b0000101011101011 &
0'
1(
#164
0(
#165
b00000000000000000000000001010010 #
b00000000000000000000000000101010 $
b0001010111010110 &
1(
#166
0(
#167
b00000000000000000000000001010011 #
b00000000000000000000000000101011 $
b0010101110101100 &
1'
1(
#168
0(
#169
b00000000000000000000000001010100 #
b00000000000000000000000000101100 $
b0101011101011001 &
0'
1(
#170
0(
#171
b00000000000000000000000001010101 #
b00000000000000000000000000101101 $
0%
b1010111010110010 &
1'
1(
#172
0(
#173
b00000000000000000000000001010110 #
1%
b0101110101100101 &
0'
1(
#174
0(
#175
b00000000000000000000000001010111 #
b00000000000000000000000000101110 $
0%
b1011101011001010 &
1'
1(
#176
0(
#177
b00000000000000000000000001011000 #
1%
b0111010110010101 &
1(
#178
0(
#179
b00000000000000000000000001011001 #
b00000000000000000000000000101111 $
0%
b1110101100101011 &
0'
1(
#180
0(
#181
b00000000000000000000000001011010 #
b1101011001010110 &
1'
1(
#182
0(
#183
b00000000000000000000000001011011 #
b1010110010101101 &
1(
#184
0(
#185
b00000000000000000000000001011100 #
1%
b0101100101011011 &
1(
#186
0(
#187
b00000000000000000000000001011101 #
b00000000000000000000000000110000 $
0%
b1011001010110111 &
1(
#188
0(
#189
b00000000000000000000000001011110 #
1%
b0110010101101111 &
0'
1(
#190
0(
#191
b00000000000000000000000001011111 #
b00000000000000000000000000110001 $
0%
b1100101011011110 &
1'
1(
#192
0(
#193
b00000000000000000000000001100000 #
b1001010110111101 &
1(
#194
0(
#195
b00000000000000000000000001100001 #
1%
b0010101101111011 &
1(
#196
0(
#197
b00000000000000000000000001100010 #
b00000000000000000000000000110010 $
b0101011011110111 &
0'
1(
#198
0(
#199
b00000000000000000000000001100011 #
b00000000000000000000000000110011 $
0%
b1010110111101110 &
1'
1(
#200
0(
#201
b00000000000000000000000001100100 #
1%
b0101101111011101 &
1(
#202
0(
#203
b00000000000000000000000001100101 #
b00000000000000000000000000110100 $
0%
b1011011110111011 &
0'
1(
#204
0(
#205
b00000000000000000000000001100110 #
1%
b0110111101110110 &
1(
#206
0(
#207
b00000000000000000000000001100111 #
b00000000000000000000000000110101 $
0%
b1101111011101100 &
1'
1(
#208
0(
#209
b00000000000000000000000001101000 #
b1011110111011001 &
0'
1(
#210
0(
#211
b00000000000000000000000001101001 #
1%
b0111101110110010 &
1(
#212
0(
#213
b00000000000000000000000001101010 #
b00000000000000000000000000110110 $
0%
b1111011101100100 &
1(
#214
0(
#215
b00000000000000000000000001101011 #
b1110111011001000 &
1'
1(
#216
0(
#217
b00000000000000000000000001101100 #
b1101110110010001 &
1(
#218
0(
#219
b00000000000000000000000001101101 #
b1011101100100011 &
1(
#220
0(
#221
b00000000000000000000000001101110 #
1%
b0111011001000111 &
1(
#222
0(
#223
b00000000000000000000000001101111 #
b00000000000000000000000000110111 $
0%
b1110110010001111 &
1(
#224
0(
#225
b00000000000000000000000001110000 #
b1101100100011111 &
0'
1(
#226
0(
#227
b00000000000000000000000001110001 #
b1011001000111110 &
1'
1(
#228
0(
#229
b00000000000000000000000001110010 #
1%
b0110010001111101 &
0'
1(
#230
0(
#231
b00000000000000000000000001110011 #
b00000000000000000000000000111000 $
0%
b1100100011111010 &
1'
1(
#232
0(
#233
b00000000000000000000000001110100 #
b1001000111110101 &
0'
1(
#234
0(
#235
b00000000000000000000000001110101 #
1%
b0010001111101010 &
1'
1(
#236
0(
#237
b00000000000000000000000001110110 #
b00000000000000000000000000111001 $
b0100011111010101 &
1(
#238
0(
#239
b00000000000000000000000001110111 #
b00000000000000000000000000111010 $
0%
b1000111110101011 &
0'
1(
#240
0(
#241
b00000000000000000000000001111000 #
1%
b0001111101010110 &
1(
#242
0(
#243
b00000000000000000000000001111001 #
b00000000000000000000000000111011 $
b0011111010101100 &
1'
1(
#244
0(
#245
b00000000000000000000000001111010 #
b00000000000000000000000000111100 $
b0111110101011001 &
1(
#246
0(
#247
b00000000000000000000000001111011 #
b00000000000000000000000000111101 $
0%
b1111101010110011 &
1(
#248
0(
#249
b00000000000000000000000001111100 #
b1111010101100111 &
0'
1(
#250
0(
#251
b00000000000000000000000001111101 #
b1110101011001110 &
1(
#252
0(
#253
b00000000000000000000000001111110 #
b1101010110011100 &
1'
1(
#254
0(
#255
b00000000000000000000000001111111 #
b1010101100111001 &
0'
1(
#256
0(
#257
b00000000000000000000000010000000 #
1%
b0101011001110010 &
1(
#258
0(
#259
b00000000000000000000000010000001 #
b00000000000000000000000000111110 $
0%
b1010110011100100 &
1'
1(
#260
0(
#261
b00000000000000000000000010000010 #
1%
b0101100111001001 &
1(
#262
0(
#263
b00000000000000000000000010000011 #
b00000000000000000000000000111111 $
0%
b1011001110010011 &
1(
#264
0(
#265
b00000000000000000000000010000100 #
1%
b0110011100100111 &
0'
1(
#266
0(
#267
b00000000000000000000000010000101 #
b00000000000000000000000001000000 $
0%
b1100111001001110 &
1(
#268
0(
#269
b00000000000000000000000010000110 #
b1001110010011100 &
1'
1(
#270
0(
#271
b00000000000000000000000010000111 #
1%
b0011100100111001 &
0'
1(
#272
0(
#273
b00000000000000000000000010001000 #
b00000000000000000000000001000001 $
b0111001001110010 &
1(
#274
0(
#275
b00000000000000000000000010001001 #
b00000000000000000000000001000010 $
0%
b1110010011100100 &
1'
1(
#276
0(
#277
b00000000000000000000000010001010 #
b1100100111001001 &
1(
#278
0(
#279
b00000000000000000000000010001011 #
b1001001110010011 &
0'
1(
#280
0(
#281
b00000000000000000000000010001100 #
1%
b0010011100100110 &
1(
#282
0(
#283
b00000000000000000000000010001101 #
b00000000000000000000000001000011 $
b0100111001001100 &
1'
1(
#284
0(
#285
b00000000000000000000000010001110 #
b00000000000000000000000001000100 $
0%
b1001110010011001 &
1(
#286
0(
#287
b00000000000000000000000010001111 #
1%
b0011100100110011 &
0'
1(
#288
0(
#289
b00000000000000000000000010010000 #
b00000000000000000000000001000101 $
b0111001001100110 &
1(
#290
0(
#291
b00000000000000000000000010010001 #
b00000000000000000000000001000110 $
0%
b1110010011001100 &
1'
1(
#292
0(
#293
b00000000000000000000000010010010 #
b1100100110011001 &
1(
#294
0(
#295
b00000000000000000000000010010011 #
b1001001100110011 &
0'
1(
#296
0(
#297
b00000000000000000000000010010100 #
1%
b0010011001100110 &
1(
#298
0(
#299
b00000000000000000000000010010101 #
b00000000000000000000000001000111 $
b0100110011001100 &
1'
1(
#300
0(
#301
b00000000000000000000000010010110 #
b00000000000000000000000001001000 $
0%
b1001100110011001 &
0'
1(
#302
0(
#303
b00000000000000000000000010010111 #
1%
b0011001100110010 &
1(
#304
0(
#305
b00000000000000000000000010011000 #
b00000000000000000000000001001001 $
b0110011001100100 &
1(
#306
0(
#307
b00000000000000000000000010011001 #
b00000000000000000000000001001010 $
0%
b1100110011001000 &
1(
#308
0(
#309
b00000000000000000000000010011010 #
b1001100110010000 &
1(
#310
0(
#311
b00000000000000000000000010011011 #
1%
b0011001100100000 &
1(
#312
0(
#313
b00000000000000000000000010011100 #
b00000000000000000000000001001011 $
b0110011001000000 &
1(
#314
0(
#315
b00000000000000000000000010011101 #
b00000000000000000000000001001100 $
0%
b1100110010000000 &
1(
#316
0(
#317
b00000000000000000000000010011110 #
b1001100100000000 &
1(
#318
0(
#319
b00000000000000000000000010011111 #
1%
b0011001000000000 &
1(
#320
0(
#321
b00000000000000000000000010100000 #
b00000000000000000000000001001101 $
b0110010000000000 &
1(
#322
0(
#323
b00000000000000000000000010100001 #
b00000000000000000000000001001110 $
0%
b1100100000000000 &
1'
1(
#324
0(
#325
b00000000000000000000000010100010 #
b1001000000000001 &
0'
1(
#326
0(
#327
b00000000000000000000000010100011 #
1%
b0010000000000010 &
1'
1(
#328
0(
#329
b00000000000000000000000010100100 #
b00000000000000000000000001001111 $
b0100000000000101 &
0'
1(
#330
0(
#331
b00000000000000000000000010100101 #
b00000000000000000000000001010000 $
0%
b1000000000001010 &
1'
1(
#332
0(
#333
b00000000000000000000000010100110 #
1%
b0000000000010101 &
0'
1(
#334
0(
#335
b00000000000000000000000010100111 #
b00000000000000000000000001010001 $
b0000000000101010 &
1(
#336
0(
#337
b00000000000000000000000010101000 #
b00000000000000000000000001010010 $
b0000000001010100 &
1(
#338
0(
#339
b00000000000000000000000010101001 #
b00000000000000000000000001010011 $
b0000000010101000 &
1(
#340
0(
#341
b00000000000000000000000010101010 #
b00000000000000000000000001010100 $
b0000000101010000 &
1(
#342
0(
#343
b00000000000000000000000010101011 #
b00000000000000000000000001010101 $
b0000001010100000 &
1(
#344
0(
#345
b00000000000000000000000010101100 #
b00000000000000000000000001010110 $
b0000010101000000 &
1'
1(
#346
0(
#347
b00000000000000000000000010101101 #
b00000000000000000000000001010111 $
b0000101010000001 &
0'
1(
#348
0(
#349
b00000000000000000000000010101110 #
b00000000000000000000000001011000 $
b0001010100000010 &
1(
#350
0(
#351
b00000000000000000000000010101111 #
b00000000000000000000000001011001 $
b0010101000000100 &
1'
1(
#352
0(
#353
b00000000000000000000000010110000 #
b00000000000000000000000001011010 $
b0101010000001001 &
0'
1(
#354
0(
#355
b00000000000000000000000010110001 #
b00000000000000000000000001011011 $
0%
b1010100000010010 &
1(
#356
0(
#357
b00000000000000000000000010110010 #
1%
b0101000000100100 &
1'
1(
#358
0(
#359
b00000000000000000000000010110011 #
b00000000000000000000000001011100 $
0%
b1010000001001001 &
0'
1(
#360
0(
#361
b00000000000000000000000010110100 #
1%
b0100000010010010 &
1(
#362
0(
#363
b00000000000000000000000010110101 #
b00000000000000000000000001011101 $
0%
b1000000100100100 &
1'
1(
#364
0(
#365
b00000000000000000000000010110110 #
1%
b0000001001001001 &
0'
1(
#366
0(
#367
b00000000000000000000000010110111 #
b00000000000000000000000001011110 $
b0000010010010010 &
1'
1(
#368
0(
#369
b00000000000000000000000010111000 #
b00000000000000000000000001011111 $
b0000100100100101 &
0'
1(
#370
0(
#371
b00000000000000000000000010111001 #
b00000000000000000000000001100000 $
b0001001001001010 &
1'
1(
#372
0(
#373
b00000000000000000000000010111010 #
b00000000000000000000000001100001 $
b0010010010010101 &
0'
1(
#374
0(
#375
b00000000000000000000000010111011 #
b00000000000000000000000001100010 $
b0100100100101010 &
1(
#376
0(
#377
b00000000000000000000000010111100 #
b00000000000000000000000001100011 $
0%
b1001001001010100 &
1(
#378
0(
#379
b00000000000000000000000010111101 #
1%
b0010010010101000 &
1(
#380
0(
#381
b00000000000000000000000010111110 #
b00000000000000000000000001100100 $
b0100100101010000 &
1(
#382
0(
#383
b00000000000000000000000010111111 #
b00000000000000000000000001100101 $
0%
b1001001010100000 &
1(
#384
0(
#385
b00000000000000000000000011000000 #
1%
b0010010101000000 &
1(
#386
0(
#387
b00000000000000000000000011000001 #
b00000000000000000000000001100110 $
b0100101010000000 &
1(
#388
0(
#389
b00000000000000000000000011000010 #
b00000000000000000000000001100111 $
0%
b1001010100000000 &
1'
1(
#390
0(
#391
b00000000000000000000000011000011 #
1%
b0010101000000001 &
1(
#392
0(
#393
b00000000000000000000000011000100 #
b00000000000000000000000001101000 $
b0101010000000011 &
0'
1(
#394
0(
#395
b00000000000000000000000011000101 #
b00000000000000000000000001101001 $
0%
b1010100000000110 &
1(
#396
0(
#397
b00000000000000000000000011000110 #
1%
b0101000000001100 &
1'
1(
#398
0(
#399
b00000000000000000000000011000111 #
b00000000000000000000000001101010 $
0%
b1010000000011001 &
0'
1(
#400
0(
#401
b00000000000000000000000011001000 #
1%
b0100000000110010 &
1(
#402
0(
#403
b00000000000000000000000011001001 #
b00000000000000000000000001101011 $
0%
b1000000001100100 &
1'
1(
#404
0(
#405
b00000000000000000000000011001010 #
1%
b0000000011001001 &
0'
1(
#406
0(
#407
b00000000000000000000000011001011 #
b00000000000000000000000001101100 $
b0000000110010010 &
1(
#408
0(
#409
b00000000000000000000000011001100 #
b00000000000000000000000001101101 $
b0000001100100100 &
1(
#410
0(
#411
b00000000000000000000000011001101 #
b00000000000000000000000001101110 $
b0000011001001000 &
1'
1(
#412
0(
#413
b00000000000000000000000011001110 #
b00000000000000000000000001101111 $
b0000110010010001 &
1(
#414
0(
#415
b00000000000000000000000011001111 #
b00000000000000000000000001110000 $
b0001100100100011 &
1(
#416
0(
#417
b00000000000000000000000011010000 #
b00000000000000000000000001110001 $
b0011001001000111 &
0'
1(
#418
0(
#419
b00000000000000000000000011010001 #
b00000000000000000000000001110010 $
b0110010010001110 &
1(
#420
0(
#421
b00000000000000000000000011010010 #
b00000000000000000000000001110011 $
0%
b1100100100011100 &
1'
1(
#422
0(
#423
b00000000000000000000000011010011 #
b1001001000111001 &
0'
1(
#424
0(
#425
b00000000000000000000000011010100 #
1%
b0010010001110010 &
1(
#426
0(
#427
b00000000000000000000000011010101 #
b00000000000000000000000001110100 $
b0100100011100100 &
1(
#428
0(
#429
b00000000000000000000000011010110 #
b00000000000000000000000001110101 $
0%
b1001000111001000 &
1(
#430
0(
#431
b00000000000000000000000011010111 #
1%
b0010001110010000 &
1'
1(
#432
0(
#433
b00000000000000000000000011011000 #
b00000000000000000000000001110110 $
b0100011100100001 &
1(
#434
0(
#435
b00000000000000000000000011011001 #
b00000000000000000000000001110111 $
0%
b1000111001000011 &
0'
1(
#436
0(
#437
b00000000000000000000000011011010 #
1%
b0001110010000110 &
1(
#438
0(
#439
b00000000000000000000000011011011 #
b00000000000000000000000001111000 $
b0011100100001100 &
1(
#440
0(
#441
b00000000000000000000000011011100 #
b00000000000000000000000001111001 $
b0111001000011000 &
1(
#442
0(
#443
b00000000000000000000000011011101 #
b00000000000000000000000001111010 $
0%
b1110010000110000 &
1'
1(
#444
0(
#445
b00000000000000000000000011011110 #
b1100100001100001 &
1(
#446
0(
#447
b00000000000000000000000011011111 #
b1001000011000011 &
0'
1(
#448
0(
#449
b00000000000000000000000011100000 #
1%
b0010000110000110 &
1'
1(
#450
0(
#451
b00000000000000000000000011100001 #
b00000000000000000000000001111011 $
b0100001100001101 &
0'
1(
#452
0(
#453
b00000000000000000000000011100010 #
b00000000000000000000000001111100 $
0%
b1000011000011010 &
1(
#454
0(
#455
b00000000000000000000000011100011 #
1%
b0000110000110100 &
1'
1(
#456
0(
#457
b00000000000000000000000011100100 #
b00000000000000000000000001111101 $
b0001100001101001 &
1(
#458
0(
#459
b00000000000000000000000011100101 #
b00000000000000000000000001111110 $
b0011000011010011 &
0'
1(
#460
0(
#461
b00000000000000000000000011100110 #
b00000000000000000000000001111111 $
b0110000110100110 &
1'
1(
#462
0(
#463
b00000000000000000000000011100111 #
b00000000000000000000000010000000 $
0%
b1100001101001101 &
1(
#464
0(
#465
b00000000000000000000000011101000 #
b1000011010011011 &
0'
1(
#466
0(
#467
b00000000000000000000000011101001 #
1%
b0000110100110110 &
1'
1(
#468
0(
#469
b00000000000000000000000011101010 #
b00000000000000000000000010000001 $
b0001101001101101 &
1(
#470
0(
#471
b00000000000000000000000011101011 #
b00000000000000000000000010000010 $
b0011010011011011 &
1(
#472
0(
#473
b00000000000000000000000011101100 #
b00000000000000000000000010000011 $
b0110100110110111 &
1(
#474
0(
#475
b00000000000000000000000011101101 #
b00000000000000000000000010000100 $
0%
b1101001101101111 &
0'
1(
#476
0(
#477
b00000000000000000000000011101110 #
b1010011011011110 &
1'
1(
#478
0(
#479
b00000000000000000000000011101111 #
1%
b0100110110111101 &
1(
#480
0(
#481
b00000000000000000000000011110000 #
b00000000000000000000000010000101 $
0%
b1001101101111011 &
0'
1(
#482
0(
#483
b00000000000000000000000011110001 #
1%
b0011011011110110 &
1'
1(
#484
0(
#485
b00000000000000000000000011110010 #
b00000000000000000000000010000110 $
b0110110111101101 &
0'
1(
#486
0(
#487
b00000000000000000000000011110011 #
b00000000000000000000000010000111 $
0%
b1101101111011010 &
1(
#488
0(
#489
b00000000000000000000000011110100 #
b1011011110110100 &
1(
#490
0(
#491
b00000000000000000000000011110101 #
1%
b0110111101101000 &
1(
#492
0(
#493
b00000000000000000000000011110110 #
b00000000000000000000000010001000 $
0%
b1101111011010000 &
1'
1(
#494
0(
#495
b00000000000000000000000011110111 #
b1011110110100001 &
0'
1(
#496
0(
#497
b00000000000000000000000011111000 #
1%
b0111101101000010 &
1(
#498
0(
#499
b00000000000000000000000011111001 #
b00000000000000000000000010001001 $
0%
b1111011010000100 &
1(
#500
0(
#501
b00000000000000000000000011111010 #
b1110110100001000 &
1'
1(
#502
0(
#503
b00000000000000000000000011111011 #
b1101101000010001 &
0'
1(
#504
0(
#505
b00000000000000000000000011111100 #
b1011010000100010 &
1(
#506
0(
#507
b00000000000000000000000011111101 #
1%
b0110100001000100 &
1'
1(
#508
0(
#509
b00000000000000000000000011111110 #
b00000000000000000000000010001010 $
0%
b1101000010001001 &
0'
1(
#510
0(
#511
b00000000000000000000000011111111 #
b1010000100010010 &
1(
#512
0(
#513
b00000000000000000000000100000000 #
1%
b0100001000100100 &
1(
#514
0(
#515
b00000000000000000000000100000001 #
b00000000000000000000000010001011 $
0%
b1000010001001000 &
1(
#516
0(
#517
b00000000000000000000000100000010 #
1%
b0000100010010000 &
1(
#518
0(
#519
b00000000000000000000000100000011 #
b00000000000000000000000010001100 $
b0001000100100000 &
1'
1(
#520
0(
#521
b00000000000000000000000100000100 #
b00000000000000000000000010001101 $
b0010001001000001 &
1(
#522
0(
#523
b00000000000000000000000100000101 #
b00000000000000000000000010001110 $
b0100010010000011 &
1(
#524
0(
#525
b00000000000000000000000100000110 #
b00000000000000000000000010001111 $
0%
b1000100100000111 &
1(
#526
0(
#527
b00000000000000000000000100000111 #
1%
b0001001000001111 &
1(
#528
0(
#529
b00000000000000000000000100001000 #
b00000000000000000000000010010000 $
b0010010000011111 &
0'
1(
#530
0(
#531
b00000000000000000000000100001001 #
b00000000000000000000000010010001 $
b0100100000111110 &
1(
#532
0(
#533
b00000000000000000000000100001010 #
b00000000000000000000000010010010 $
0%
b1001000001111100 &
1(
#534
0(
#535
b00000000000000000000000100001011 #
1%
b0010000011111000 &
1'
1(
#536
0(
#537
b00000000000000000000000100001100 #
b00000000000000000000000010010011 $
b0100000111110001 &
0'
1(
#538
0(
#539
b00000000000000000000000100001101 #
b00000000000000000000000010010100 $
0%
b1000001111100010 &
1'
1(
#540
0(
#541
b00000000000000000000000100001110 #
1%
b0000011111000101 &
1(
#542
0(
#543
b00000000000000000000000100001111 #
b00000000000000000000000010010101 $
b0000111110001011 &
1(
#544
0(
#545
b00000000000000000000000100010000 #
b00000000000000000000000010010110 $
b0001111100010111 &
0'
1(
#546
0(
#547
b00000000000000000000000100010001 #
b00000000000000000000000010010111 $
b0011111000101110 &
1'
1(
#548
0(
#549
b00000000000000000000000100010010 #
b00000000000000000000000010011000 $
b0111110001011101 &
1(
#550
0(
#551
b00000000000000000000000100010011 #
b00000000000000000000000010011001 $
0%
b1111100010111011 &
1(
#552
0(
#553
b00000000000000000000000100010100 #
b1111000101110111 &
1(
#554
0(
#555
b00000000000000000000000100010101 #
b1110001011101111 &
0'
1(
#556
0(
#557
b00000000000000000000000100010110 #
b1100010111011110 &
1(
#558
0(
#559
b00000000000000000000000100010111 #
b1000101110111100 &
1'
1(
#560
0(
#561
b00000000000000000000000100011000 #
1%
b0001011101111001 &
0'
1(
#562
0(
#563
b00000000000000000000000100011001 #
b00000000000000000000000010011010 $
b0010111011110010 &
1(
#564
0(
#565
b00000000000000000000000100011010 #
b00000000000000000000000010011011 $
b0101110111100100 &
1(
#566
0(
#567
b00000000000000000000000100011011 #
b00000000000000000000000010011100 $
0%
b1011101111001000 &
1'
1(
#568
0(
#569
b00000000000000000000000100011100 #
1%
b0111011110010001 &
1(
#570
0(
#571
b00000000000000000000000100011101 #
b00000000000000000000000010011101 $
0%
b1110111100100011 &
1(
#572
0(
#573
b00000000000000000000000100011110 #
b1101111001000111 &
1(
#574
0(
#575
b00000000000000000000000100011111 #
b1011110010001111 &
0'
1(
#576
0(
#577
b00000000000000000000000100100000 #
1%
b0111100100011110 &
1(
#578
0(
